openql/__init__.py
openql/_openql.cpython-312-x86_64-linux-gnu.so
openql/openql.py
qutechopenql-0.12.2.dist-info/WHEEL
qutechopenql-0.12.2.dist-info/RECORD
qutechopenql-0.12.2.dist-info/LICENSE.md
qutechopenql-0.12.2.dist-info/top_level.txt
qutechopenql-0.12.2.dist-info/METADATA
