Metadata-Version: 2.1
Name: qutechopenql
Version: 0.12.2
Summary: OpenQL Python Package
Home-page: https://github.com/QuTech-Delft/OpenQL
Author: QuTech, TU Delft
Classifier: License :: OSI Approved :: Apache Software License
Classifier: Operating System :: POSIX :: Linux
Classifier: Operating System :: MacOS
Classifier: Operating System :: Microsoft :: Windows
Classifier: Programming Language :: Python :: 3 :: Only
Classifier: Programming Language :: Python :: 3.8
Classifier: Programming Language :: Python :: 3.9
Classifier: Programming Language :: Python :: 3.10
Classifier: Programming Language :: Python :: 3.11
Classifier: Programming Language :: Python :: 3.12
Classifier: Topic :: Scientific/Engineering
License-File: LICENSE.md
Requires-Dist: msvc-runtime ; platform_system == "Windows"
